discord_timestamps/__init__.py
discord_timestamps/formats.py
discord_timestamps-1.0.2.dist-info/LICENSE
discord_timestamps-1.0.2.dist-info/WHEEL
discord_timestamps-1.0.2.dist-info/METADATA
discord_timestamps-1.0.2.dist-info/RECORD
