Metadata-Version: 2.1
Name: discord-timestamps
Version: 1.0.2
Summary: Generation of properly-formatted dynamic timestamps for Discord messages
Author-email: Ben Soyka <bensoyka@icloud.com>
Requires-Python: ~=3.8
Classifier: Development Status :: 5 - Production/Stable
Classifier: Intended Audience :: Developers
Classifier: Natural Language :: English
Classifier: License :: OSI Approved :: MIT License
Classifier: Programming Language :: Python
Classifier: Programming Language :: Python :: 3
Classifier: Programming Language :: Python :: 3.8
Classifier: Programming Language :: Python :: 3.9
Classifier: Programming Language :: Python :: 3.10
Classifier: Programming Language :: Python :: 3.11
Classifier: Programming Language :: Python :: 3.12
Requires-Dist: arrow~=1.3.0
Project-URL: Changelog, https://github.com/bsoyka/discord-timestamps/releases
Project-URL: Documentation, https://github.com/bsoyka/discord-timestamps/wiki
Project-URL: Source, https://github.com/bsoyka/discord-timestamps
